{
    "tools": {
        "ProcessingGeometrySuite": {
            "tags": [
                "library",
                "geometry"
            ],
            "dependsOn": [
                "Processing",
                "Jts"
            ]
        },
        "ComputationalGeometry": {
            "tags": [
                "library",
                "geometry"
            ],
            "actions": {
                "plotIsoContour": {
                    "description": "Plot isocontour in 2D",
                    "techniques": [
                        "MarchingSquares"
                    ]
                },
                "plotIsoSurface": {
                    "description": "Plot isosurface in 3D",
                    "techniques": [
                        "MarchingCubes"
                    ]
                }
            },
            "dependsOn": [
                "Processing"
            ]
        },
        "Processing": {
            "prototypes": [
                "_ImageIO",
                "_VideoIO",
                "_LibraryIO",
                "_Drawing"
            ],
            "tags": [
                "creative coding",
                "application",
                "library",
                "opensource"
            ],
            "actions": {
                "loadImageArtifact": {
                    "description": "Load image artifact",
                    "arguments": [
                        {
                            "name": "name",
                            "type": "IArtifact"
                        }
                    ]
                },
                "saveImage": {
                    "description": "Save Image",
                    "arguments": [
                        {
                            "name": "name"
                        }
                    ],
                    "outputType": "FileArtifact"
                },
                "loadImage": {
                    "description": "Load Image",
                    "arguments": [
                        {
                            "name": "name"
                        }
                    ]
                },
                "createImage": {
                    "description": "Create an image",
                    "arguments": [
                        {
                            "name": "width",
                            "type": "Int"
                        },
                        {
                            "name": "height",
                            "type": "Int"
                        }
                    ]
                },
                "loadVideo": {
                    "description": "Load Video",
                    "arguments": [
                        {
                            "name": "name"
                        }
                    ],
                    "outputType": "VideoArtifact"
                },
                "saveVideo": {
                    "description": "Save Video",
                    "arguments": [
                        {
                            "name": "name"
                        }
                    ]
                },
                "importLibrary": {
                    "description": "Import library",
                    "arguments": [
                        {
                            "name": "libraryName"
                        }
                    ],
                    "outputType": "SourceCodeArtifact"
                },
                "clearBackground": {
                    "description": "Clear the background",
                    "arguments": [
                        {
                            "name": "red",
                            "type": "Number"
                        },
                        {
                            "name": "green",
                            "type": "Number"
                        },
                        {
                            "name": "blue",
                            "type": "Number"
                        }
                    ]
                },
                "drawEllipse": {
                    "description": "Draw an ellipse",
                    "arguments": [
                        {
                            "name": "x",
                            "type": "Number"
                        },
                        {
                            "name": "y",
                            "type": "Number"
                        },
                        {
                            "name": "xRadius",
                            "type": "Number"
                        },
                        {
                            "name": "yRadius",
                            "type": "Number"
                        }
                    ]
                },
                "drawCircle": {
                    "description": "Draw a circle",
                    "arguments": [
                        {
                            "name": "x",
                            "type": "Number"
                        },
                        {
                            "name": "y",
                            "type": "Number"
                        },
                        {
                            "name": "radius",
                            "type": "Number"
                        }
                    ]
                },
                "drawLine": {
                    "description": "Draw a line",
                    "arguments": [
                        {
                            "name": "x0",
                            "type": "Number"
                        },
                        {
                            "name": "y0",
                            "type": "Number"
                        },
                        {
                            "name": "x1",
                            "type": "Number"
                        },
                        {
                            "name": "y1",
                            "type": "Number"
                        }
                    ]
                },
                "drawCubicBezier": {
                    "description": "Draw a cubic bezier curve",
                    "arguments": [
                        {
                            "name": "x0",
                            "type": "Number"
                        },
                        {
                            "name": "y0",
                            "type": "Number"
                        },
                        {
                            "name": "x1",
                            "type": "Number"
                        },
                        {
                            "name": "y1",
                            "type": "Number"
                        },
                        {
                            "name": "x2",
                            "type": "Number"
                        },
                        {
                            "name": "y2",
                            "type": "Number"
                        },
                        {
                            "name": "x3",
                            "type": "Number"
                        },
                        {
                            "name": "y3",
                            "type": "Number"
                        }
                    ]
                },
                "drawQuadraticBezier": {
                    "description": "Draw a quadratic bezier curve",
                    "arguments": [
                        {
                            "name": "x0",
                            "type": "Number"
                        },
                        {
                            "name": "y0",
                            "type": "Number"
                        },
                        {
                            "name": "x1",
                            "type": "Number"
                        },
                        {
                            "name": "y1",
                            "type": "Number"
                        },
                        {
                            "name": "x2",
                            "type": "Number"
                        },
                        {
                            "name": "y2",
                            "type": "Number"
                        }
                    ]
                },
                "setStroke": {
                    "description": "Set the stroke color",
                    "arguments": [
                        {
                            "name": "red",
                            "type": "Number"
                        },
                        {
                            "name": "green",
                            "type": "Number"
                        },
                        {
                            "name": "blue",
                            "type": "Number"
                        },
                        {
                            "name": "alpha",
                            "type": "Number"
                        }
                    ]
                },
                "setFill": {
                    "description": "Set the fill color",
                    "arguments": [
                        {
                            "name": "red",
                            "type": "Number"
                        },
                        {
                            "name": "green",
                            "type": "Number"
                        },
                        {
                            "name": "blue",
                            "type": "Number"
                        },
                        {
                            "name": "alpha",
                            "type": "Number"
                        }
                    ]
                },
                "drawRectangle": {
                    "description": "Draw a rectangle",
                    "arguments": [
                        {
                            "name": "x",
                            "type": "Number"
                        },
                        {
                            "name": "y",
                            "type": "Number"
                        },
                        {
                            "name": "width",
                            "type": "Number"
                        },
                        {
                            "name": "height",
                            "type": "Number"
                        }
                    ]
                },
                "drawImage": {
                    "description": "Draw an image",
                    "arguments": [
                        {
                            "name": "x",
                            "type": "Number"
                        },
                        {
                            "name": "y",
                            "type": "Number"
                        },
                        {
                            "name": "width",
                            "type": "Number"
                        },
                        {
                            "name": "height",
                            "type": "Number"
                        }
                    ]
                },
                "setFont": {
                    "description": "Set the active font",
                    "arguments": [
                        {
                            "name": "font"
                        },
                        {
                            "name": "size",
                            "type": "Number"
                        }
                    ]
                },
                "drawText": {
                    "description": "Draw a text",
                    "arguments": [
                        {
                            "name": "x",
                            "type": "Number"
                        },
                        {
                            "name": "y",
                            "type": "Number"
                        },
                        {
                            "name": "text"
                        }
                    ]
                },
                "drawPoint": {
                    "description": "Draw a point",
                    "arguments": [
                        {
                            "name": "x",
                            "type": "Number"
                        },
                        {
                            "name": "y",
                            "type": "Number"
                        }
                    ]
                },
                "runSketch": {
                    "description": "Run sketch"
                }
            },
            "dependsOn": [
                "Java",
                "Jogl",
                "Antlr",
                "Swing"
            ],
            "supports": [
                "Json",
                "Csv",
                "Png",
                "Jpg"
            ]
        },
        "Vulkan": {
            "tags": [
                "library",
                "graphics api"
            ],
            "references": [
                "https://en.wikipedia.org/wiki/Vulkan"
            ]
        },
        "Display": {
            "tags": [
                "media technology",
                "hardware"
            ]
        },
        "Figma": {
            "tags": [
                "application",
                "saas",
                "vector graphics",
                "raster graphics"
            ],
            "supports": [
                "Png",
                "Jpg",
                "Json"
            ]
        },
        "SuperCollider": {
            "tags": [
                "application",
                "opensource",
                "audio"
            ]
        },
        "Camera": {
            "tags": [
                "media technology",
                "sensor",
                "hardware"
            ],
            "actions": {
                "capture": {
                    "description": "Capture a frame"
                }
            }
        },
        "Pico8": {
            "tags": [
                "fantasy console"
            ],
            "references": [
                "https://en.wikipedia.org/wiki/PICO-8"
            ],
            "dependsOn": [
                "Lua"
            ]
        },
        "OpenGL": {
            "tags": [
                "library",
                "graphics api"
            ],
            "references": [
                "https://en.wikipedia.org/wiki/OpenGL"
            ]
        },
        "HLSL": {
            "tags": [
                "language",
                "shaders"
            ],
            "references": [
                "https://en.wikipedia.org/wiki/High-Level_Shader_Language"
            ],
            "dependsOn": [
                "Direct3D"
            ]
        },
        "Audacity": {
            "tags": [
                "application",
                "audio"
            ],
            "supports": [
                "Mp3",
                "Ogg"
            ]
        },
        "MaxMsp": {
            "tags": [
                "application",
                "node-based"
            ]
        },
        "Sox": {
            "tags": [
                "application",
                "audio",
                "command-line",
                "opensource"
            ],
            "references": [
                "https://en.wikipedia.org/wiki/SoX"
            ],
            "supports": [
                "Mp3",
                "Ogg",
                "Wav"
            ]
        },
        "WebGPU": {
            "tags": [
                "library",
                "graphics api",
                "web"
            ],
            "references": [
                "https://en.wikipedia.org/wiki/WebGPU"
            ]
        },
        "Cinema4D": {
            "tags": [
                "application",
                "3d graphics"
            ],
            "references": [
                "https://en.wikipedia.org/wiki/Cinema_4D"
            ]
        },
        "Angle": {
            "tags": [
                "library",
                "graphics api"
            ],
            "references": [
                "https://en.wikipedia.org/wiki/ANGLE_(software)"
            ],
            "dependsOn": [
                "OpenGL_ES"
            ],
            "supports": [
                "Metal",
                "Vulkan",
                "Direct3D",
                "OpenGL"
            ]
        },
        "Arduino": {
            "tags": [
                "hardware",
                "microcontroller",
                "application",
                "opensource"
            ],
            "references": [
                "https://en.wikipedia.org/wiki/Arduino",
                "https://www.arduino.cc/"
            ]
        },
        "CircuitPython": {
            "tags": [
                "language",
                "microcontroller",
                "opensource"
            ]
        },
        "Godot": {
            "tags": [
                "game development"
            ],
            "references": [
                "https://en.wikipedia.org/wiki/Godot_(game_engine)"
            ],
            "dependsOn": [
                "CSharp",
                "CPP"
            ]
        },
        "Metal": {
            "tags": [
                "library",
                "graphics api"
            ],
            "references": [
                "https://en.wikipedia.org/wiki/Metal_(API)"
            ]
        },
        "Cinder": {
            "tags": [
                "creative coding",
                "library",
                "opensource"
            ],
            "references": [
                "https://en.wikipedia.org/wiki/Cinder_(programming_library)"
            ],
            "dependsOn": [
                "CPP"
            ]
        },
        "Inkscape": {
            "tags": [
                "application",
                "opensource",
                "vector graphics"
            ],
            "references": [
                "https://en.wikipedia.org/wiki/Inkscape"
            ],
            "supports": [
                "Svg"
            ]
        },
        "OpenProcessing": {
            "tags": [
                "creative coding",
                "platform"
            ],
            "dependsOn": [
                "P5Js"
            ]
        },
        "MediaPlayer": {
            "tags": [
                "media technology",
                "hardware"
            ],
            "actions": {
                "play": {
                    "description": "Play media"
                },
                "stop": {
                    "description": "Stop media"
                }
            }
        },
        "DepthSensor": {
            "tags": [
                "media technology",
                "sensor",
                "hardware"
            ],
            "actions": {
                "capture": {
                    "description": "Capture a frame"
                }
            }
        },
        "Picotron": {
            "tags": [
                "fantasy console"
            ],
            "references": [
                "https://en.wikipedia.org/wiki/Picotron",
                "https://www.lexaloffle.com/picotron.php"
            ],
            "dependsOn": [
                "Lua"
            ]
        },
        "Lua": {
            "tags": [
                "language"
            ],
            "references": [
                "https://en.wikipedia.org/wiki/Lua_(programming_language)"
            ]
        },
        "Projector": {
            "tags": [
                "media technology",
                "hardware"
            ],
            "actions": {
                "display": {
                    "description": "Project on surface",
                    "arguments": [
                        {
                            "name": "artifact",
                            "type": "IArtifact"
                        }
                    ],
                    "outputType": "PrintedArtifact"
                }
            }
        },
        "MidiKeyboard": {
            "tags": [
                "media technology",
                "hardware"
            ],
            "dependsOn": [
                "Midi"
            ]
        },
        "Rust": {
            "tags": [
                "language",
                "opensource"
            ]
        },
        "Photoshop": {
            "tags": [
                "application",
                "raster graphics"
            ],
            "supports": [
                "Png",
                "Jpg",
                "Gif"
            ]
        },
        "Ruby": {
            "tags": [
                "language",
                "opensource"
            ]
        },
        "C": {
            "tags": [
                "language"
            ]
        },
        "D3JS": {
            "tags": [
                "library",
                "web",
                "opensource"
            ],
            "supports": [
                "Csv",
                "Json",
                "Svg"
            ]
        },
        "ShaderToy": {
            "tags": [
                "software",
                "platform",
                "web",
                "shaders"
            ],
            "references": [
                "https://www.shadertoy.com/",
                "https://en.wikipedia.org/wiki/Shadertoy"
            ],
            "actions": {
                "runShader": {
                    "description": "Run Shader"
                },
                "publishShader": {
                    "description": " Publish shader",
                    "outputType": "SourceCodeArtifact"
                }
            },
            "dependsOn": [
                "Javascript",
                "WebGL"
            ],
            "supports": [
                "GLSL"
            ]
        },
        "OpenFrameworks": {
            "tags": [
                "creative coding",
                "opensource"
            ],
            "references": [
                "https://en.wikipedia.org/wiki/OpenFrameworks"
            ],
            "dependsOn": [
                "CPP"
            ]
        },
        "Ktor": {
            "dependsOn": [
                "Kotlin"
            ],
            "supports": [
                "Http",
                "Https",
                "WebSocket"
            ]
        },
        "PenPlotter": {
            "tags": [
                "media technology",
                "hardware",
                "print"
            ],
            "actions": {
                "plot": {
                    "description": "Plot on paper",
                    "arguments": [
                        {
                            "name": "artifact",
                            "type": "IArtifact"
                        }
                    ],
                    "outputType": "PrintedArtifact"
                }
            }
        },
        "Nannou": {
            "tags": [
                "creative coding",
                "library",
                "opensource"
            ],
            "references": [
                "https://nannou.cc/"
            ],
            "dependsOn": [
                "Rust"
            ]
        },
        "OpenGL_ES": {
            "tags": [
                "library",
                "graphics api"
            ],
            "references": [
                "https://en.wikipedia.org/wiki/OpenGL_ES"
            ]
        },
        "Hydra": {
            "tags": [
                "creative coding",
                "shaders",
                "opensource"
            ],
            "references": [
                "https://hydra.ojack.xyz/"
            ],
            "dependsOn": [
                "Browser"
            ]
        },
        "WebGL": {
            "tags": [
                "library",
                "graphics api",
                "web"
            ],
            "references": [
                "https://en.wikipedia.org/wiki/WebGL"
            ]
        },
        "GLSL": {
            "tags": [
                "language",
                "shaders"
            ],
            "references": [
                "https://en.wikipedia.org/wiki/OpenGL_Shading_Language"
            ],
            "dependsOn": [
                "OpenGL"
            ]
        },
        "Midi": {
            "tags": [
                "standard",
                "device interface"
            ],
            "references": [
                "https://en.wikipedia.org/wiki/MIDI"
            ]
        },
        "Gimp": {
            "tags": [
                "application",
                "opensource",
                "raster graphics"
            ],
            "supports": [
                "Png",
                "Jpg",
                "Gif"
            ]
        },
        "Printer": {
            "tags": [
                "media technology",
                "hardware",
                "print"
            ],
            "actions": {
                "print": {
                    "description": "Print on paper",
                    "outputType": "PrintedArtifact"
                }
            }
        },
        "Browser": {
            "tags": [
                "application",
                "web"
            ],
            "supports": [
                "Http",
                "Https",
                "WebGL",
                "Javascript",
                "WebSocket",
                "Gif",
                "Jpg",
                "Html",
                "Svg",
                "Wav"
            ]
        },
        "Illustrator": {
            "tags": [
                "application",
                "vector graphics"
            ],
            "references": [
                "https://en.wikipedia.org/wiki/Adobe_Illustrator"
            ],
            "supports": [
                "Svg"
            ]
        },
        "MidiController": {
            "tags": [
                "media technology",
                "hardware"
            ],
            "dependsOn": [
                "Midi"
            ]
        },
        "MicroPython": {
            "tags": [
                "language",
                "microcontroller",
                "opensource"
            ],
            "references": [
                "https://en.wikipedia.org/wiki/MicroPython"
            ]
        },
        "PaperJs": {
            "tags": [
                "web",
                "library",
                "opensource"
            ],
            "references": [
                "http://paperjs.org/"
            ],
            "dependsOn": [
                "Javascript"
            ]
        },
        "Microphone": {
            "tags": [
                "media technology",
                "hardware"
            ],
            "actions": {
                "capture": {
                    "description": "Capture sound",
                    "outputType": "AudioArtifact"
                }
            }
        },
        "PureData": {
            "tags": [
                "application",
                "opensource",
                "node-based"
            ]
        },
        "VSCode": {
            "tags": [
                "application",
                "ide",
                "opensource"
            ],
            "references": [
                "https://en.wikipedia.org/wiki/Visual_Studio_Code"
            ]
        },
        "Direct3D": {
            "tags": [
                "library",
                "graphics api"
            ],
            "references": [
                "https://en.wikipedia.org/wiki/Direct3D"
            ]
        },
        "Unity": {
            "tags": [
                "game development"
            ],
            "references": [
                "https://en.wikipedia.org/wiki/Unity_(game_engine)"
            ],
            "dependsOn": [
                "CSharp",
                "CPP"
            ]
        },
        "Kotlin": {
            "tags": [
                "language"
            ],
            "references": [
                "https://kotlinlang.org/"
            ],
            "supports": [
                "Java",
                "Javascript"
            ]
        },
        "IntelliJ": {
            "tags": [
                "application",
                "ide"
            ],
            "references": [
                "https://en.wikipedia.org/wiki/IntelliJ_IDEA"
            ]
        },
        "P5Js": {
            "prototypes": [
                "_ImageIO",
                "_VideoIO",
                "_LibraryIO",
                "_Drawing"
            ],
            "tags": [
                "creative coding",
                "application",
                "library",
                "web",
                "opensource"
            ],
            "references": [
                "https://en.wikipedia.org/wiki/Processing#p5.js"
            ],
            "actions": {
                "loadImageArtifact": {
                    "description": "Load image artifact",
                    "arguments": [
                        {
                            "name": "name",
                            "type": "IArtifact"
                        }
                    ]
                },
                "saveImage": {
                    "description": "Save Image",
                    "arguments": [
                        {
                            "name": "name"
                        }
                    ],
                    "outputType": "FileArtifact"
                },
                "loadImage": {
                    "description": "Load Image",
                    "arguments": [
                        {
                            "name": "name"
                        }
                    ]
                },
                "createImage": {
                    "description": "Create an image",
                    "arguments": [
                        {
                            "name": "width",
                            "type": "Int"
                        },
                        {
                            "name": "height",
                            "type": "Int"
                        }
                    ]
                },
                "loadVideo": {
                    "description": "Load Video",
                    "arguments": [
                        {
                            "name": "name"
                        }
                    ],
                    "outputType": "VideoArtifact"
                },
                "saveVideo": {
                    "description": "Save Video",
                    "arguments": [
                        {
                            "name": "name"
                        }
                    ]
                },
                "importLibrary": {
                    "description": "Import library",
                    "arguments": [
                        {
                            "name": "libraryName"
                        }
                    ],
                    "outputType": "SourceCodeArtifact"
                },
                "clearBackground": {
                    "description": "Clear the background",
                    "arguments": [
                        {
                            "name": "red",
                            "type": "Number"
                        },
                        {
                            "name": "green",
                            "type": "Number"
                        },
                        {
                            "name": "blue",
                            "type": "Number"
                        }
                    ]
                },
                "drawEllipse": {
                    "description": "Draw an ellipse",
                    "arguments": [
                        {
                            "name": "x",
                            "type": "Number"
                        },
                        {
                            "name": "y",
                            "type": "Number"
                        },
                        {
                            "name": "xRadius",
                            "type": "Number"
                        },
                        {
                            "name": "yRadius",
                            "type": "Number"
                        }
                    ]
                },
                "drawCircle": {
                    "description": "Draw a circle",
                    "arguments": [
                        {
                            "name": "x",
                            "type": "Number"
                        },
                        {
                            "name": "y",
                            "type": "Number"
                        },
                        {
                            "name": "radius",
                            "type": "Number"
                        }
                    ]
                },
                "drawLine": {
                    "description": "Draw a line",
                    "arguments": [
                        {
                            "name": "x0",
                            "type": "Number"
                        },
                        {
                            "name": "y0",
                            "type": "Number"
                        },
                        {
                            "name": "x1",
                            "type": "Number"
                        },
                        {
                            "name": "y1",
                            "type": "Number"
                        }
                    ]
                },
                "drawCubicBezier": {
                    "description": "Draw a cubic bezier curve",
                    "arguments": [
                        {
                            "name": "x0",
                            "type": "Number"
                        },
                        {
                            "name": "y0",
                            "type": "Number"
                        },
                        {
                            "name": "x1",
                            "type": "Number"
                        },
                        {
                            "name": "y1",
                            "type": "Number"
                        },
                        {
                            "name": "x2",
                            "type": "Number"
                        },
                        {
                            "name": "y2",
                            "type": "Number"
                        },
                        {
                            "name": "x3",
                            "type": "Number"
                        },
                        {
                            "name": "y3",
                            "type": "Number"
                        }
                    ]
                },
                "drawQuadraticBezier": {
                    "description": "Draw a quadratic bezier curve",
                    "arguments": [
                        {
                            "name": "x0",
                            "type": "Number"
                        },
                        {
                            "name": "y0",
                            "type": "Number"
                        },
                        {
                            "name": "x1",
                            "type": "Number"
                        },
                        {
                            "name": "y1",
                            "type": "Number"
                        },
                        {
                            "name": "x2",
                            "type": "Number"
                        },
                        {
                            "name": "y2",
                            "type": "Number"
                        }
                    ]
                },
                "setStroke": {
                    "description": "Set the stroke color",
                    "arguments": [
                        {
                            "name": "red",
                            "type": "Number"
                        },
                        {
                            "name": "green",
                            "type": "Number"
                        },
                        {
                            "name": "blue",
                            "type": "Number"
                        },
                        {
                            "name": "alpha",
                            "type": "Number"
                        }
                    ]
                },
                "setFill": {
                    "description": "Set the fill color",
                    "arguments": [
                        {
                            "name": "red",
                            "type": "Number"
                        },
                        {
                            "name": "green",
                            "type": "Number"
                        },
                        {
                            "name": "blue",
                            "type": "Number"
                        },
                        {
                            "name": "alpha",
                            "type": "Number"
                        }
                    ]
                },
                "drawRectangle": {
                    "description": "Draw a rectangle",
                    "arguments": [
                        {
                            "name": "x",
                            "type": "Number"
                        },
                        {
                            "name": "y",
                            "type": "Number"
                        },
                        {
                            "name": "width",
                            "type": "Number"
                        },
                        {
                            "name": "height",
                            "type": "Number"
                        }
                    ]
                },
                "drawImage": {
                    "description": "Draw an image",
                    "arguments": [
                        {
                            "name": "x",
                            "type": "Number"
                        },
                        {
                            "name": "y",
                            "type": "Number"
                        },
                        {
                            "name": "width",
                            "type": "Number"
                        },
                        {
                            "name": "height",
                            "type": "Number"
                        }
                    ]
                },
                "setFont": {
                    "description": "Set the active font",
                    "arguments": [
                        {
                            "name": "font"
                        },
                        {
                            "name": "size",
                            "type": "Number"
                        }
                    ]
                },
                "drawText": {
                    "description": "Draw a text",
                    "arguments": [
                        {
                            "name": "x",
                            "type": "Number"
                        },
                        {
                            "name": "y",
                            "type": "Number"
                        },
                        {
                            "name": "text"
                        }
                    ]
                },
                "drawPoint": {
                    "description": "Draw a point",
                    "arguments": [
                        {
                            "name": "x",
                            "type": "Number"
                        },
                        {
                            "name": "y",
                            "type": "Number"
                        }
                    ]
                },
                "runSketch": {
                    "description": "Run sketch",
                    "outputType": "ProcessArtifact"
                },
                "publishSketch": {
                    "description": "Publish sketch",
                    "outputType": "SourceCodeArtifact"
                }
            },
            "dependsOn": [
                "Javascript"
            ]
        },
        "Javascript": {
            "tags": [
                "language",
                "web"
            ]
        },
        "CPP": {
            "tags": [
                "language"
            ],
            "references": [
                "https://en.wikipedia.org/wiki/C%2B%2B"
            ]
        },
        "Esp32": {
            "tags": [
                "hardware",
                "microcontroller"
            ],
            "references": [
                "https://en.wikipedia.org/wiki/ESP32"
            ]
        },
        "CSharp": {
            "tags": [
                "language"
            ]
        },
        "Ffmpeg": {
            "tags": [
                "application",
                "library",
                "video",
                "command-line",
                "opensource"
            ],
            "references": [
                "https://en.wikipedia.org/wiki/FFmpeg"
            ],
            "dependsOn": [
                "C"
            ],
            "supports": [
                "Mp4",
                "Mov",
                "Mp3",
                "Ogg",
                "Wav"
            ]
        },
        "ImageMagick": {
            "tags": [
                "application",
                "raster graphics",
                "vector graphics",
                "command-line",
                "opensource"
            ],
            "references": [
                "https://en.wikipedia.org/wiki/ImageMagick",
                "https://imagemagick.org/"
            ],
            "supports": [
                "Png",
                "Svg",
                "Jpg",
                "Gif"
            ]
        },
        "Nodebox": {
            "tags": [
                "application",
                "opensource",
                "node-based"
            ],
            "dependsOn": [
                "Python"
            ]
        },
        "TouchDesigner": {
            "tags": [
                "application",
                "node-based"
            ]
        },
        "Blender": {
            "tags": [
                "application",
                "opensource",
                "3d graphics"
            ],
            "references": [
                "https://en.wikipedia.org/wiki/Blender_(software)"
            ],
            "dependsOn": [
                "C",
                "Python"
            ],
            "supports": [
                "Gltf",
                "Obj"
            ]
        },
        "ThreeJS": {
            "tags": [
                "creative coding",
                "library",
                "web",
                "opensource"
            ],
            "dependsOn": [
                "Javascript",
                "WebGL",
                "WebGPU"
            ],
            "supports": [
                "GLSL",
                "Gltf"
            ]
        },
        "Tic80": {
            "tags": [
                "fantasy console"
            ],
            "references": [
                "https://en.wikipedia.org/wiki/TIC-80"
            ],
            "dependsOn": [
                "Lua"
            ]
        },
        "DMX": {
            "tags": [
                "standard",
                "device interface"
            ],
            "references": [
                "https://en.wikipedia.org/wiki/DMX"
            ]
        },
        "KotlinxSerialization": {
            "tags": [
                "library"
            ],
            "references": [
                "https://github.com/Kotlin/kotlinx.serialization"
            ],
            "dependsOn": [
                "Kotlin"
            ],
            "supports": [
                "Json",
                "Yaml",
                "Xml"
            ]
        },
        "KotlinCsv": {
            "tags": [
                "library"
            ],
            "references": [
                "https://github.com/jsoizo/kotlin-csv"
            ],
            "dependsOn": [
                "Kotlin"
            ],
            "supports": [
                "Csv"
            ]
        },
        "SDL": {
            "tags": [
                "library"
            ],
            "references": [
                "https://en.wikipedia.org/wiki/Simple_DirectMedia_Layer"
            ],
            "dependsOn": [
                "C"
            ],
            "supports": [
                "OpenGL",
                "Vulkan",
                "OpenGL_ES"
            ]
        },
        "Glfw": {
            "tags": [
                "library"
            ],
            "references": [
                "https://en.wikipedia.org/wiki/GLFW"
            ],
            "dependsOn": [
                "C"
            ],
            "supports": [
                "OpenGL",
                "Vulkan",
                "OpenGL_ES"
            ]
        },
        "PyTorch": {
            "tags": [
                "library",
                "machine learning"
            ],
            "references": [
                "https://en.wikipedia.org/wiki/PyTorch"
            ],
            "dependsOn": [
                "Python",
                "CPP"
            ]
        },
        "Pandas": {
            "tags": [
                "library",
                "data science"
            ],
            "references": [
                "https://en.wikipedia.org/wiki/Pandas_(software)"
            ],
            "dependsOn": [
                "Python"
            ],
            "supports": [
                "Json",
                "Csv"
            ]
        },
        "ScikitLearn": {
            "tags": [
                "library",
                "data science",
                "machine learning"
            ],
            "references": [
                "https://en.wikipedia.org/wiki/Scikit-learn"
            ],
            "dependsOn": [
                "Python"
            ]
        },
        "Python": {
            "tags": [
                "language",
                "opensource"
            ],
            "references": [
                "https://www.python.org/",
                "https://en.wikipedia.org/wiki/Python_(programming_language)"
            ]
        },
        "Transformers": {
            "tags": [
                "library",
                "machine learning"
            ],
            "references": [
                "https://github.com/huggingface/transformers"
            ],
            "dependsOn": [
                "Python"
            ],
            "supports": [
                "PyTorch"
            ]
        },
        "NumPy": {
            "tags": [
                "library"
            ],
            "references": [
                "https://en.wikipedia.org/wiki/NumPy"
            ],
            "dependsOn": [
                "Python"
            ]
        },
        "Mp4": {
            "tags": [
                "file format",
                "video"
            ],
            "references": [
                "https://en.wikipedia.org/wiki/MP4_file_format"
            ]
        },
        "Mp3": {
            "tags": [
                "file format",
                "audio"
            ],
            "references": [
                "https://en.wikipedia.org/wiki/MP3"
            ]
        },
        "Css": {
            "tags": [
                "file format",
                "language"
            ],
            "references": [
                "https://en.wikipedia.org/wiki/CSS"
            ]
        },
        "Collada": {
            "tags": [
                "file format",
                "3d graphics"
            ],
            "references": [
                "https://en.wikipedia.org/wiki/COLLADA"
            ]
        },
        "Svg": {
            "tags": [
                "file format",
                "vector graphics"
            ],
            "references": [
                "https://en.wikipedia.org/wiki/SVG"
            ]
        },
        "Gif": {
            "tags": [
                "file format",
                "raster graphics"
            ],
            "references": [
                "https://en.wikipedia.org/wiki/GIF"
            ]
        },
        "Mov": {
            "tags": [
                "file format",
                "video"
            ],
            "references": [
                "https://en.wikipedia.org/wiki/QuickTime_File_Format"
            ]
        },
        "Opus": {
            "tags": [
                "file format",
                "audio"
            ],
            "references": [
                "https://en.wikipedia.org/wiki/Opus_(audio_format)"
            ]
        },
        "Png": {
            "tags": [
                "file format",
                "raster graphics"
            ],
            "references": [
                "https://en.wikipedia.org/wiki/PNG"
            ]
        },
        "Yaml": {
            "tags": [
                "file format",
                "structured data"
            ],
            "references": [
                "https://en.wikipedia.org/wiki/YAML"
            ]
        },
        "Csv": {
            "tags": [
                "file format",
                "structured data"
            ],
            "references": [
                "https://en.wikipedia.org/wiki/Comma-separated_values"
            ]
        },
        "Obj": {
            "tags": [
                "file format",
                "3d graphics"
            ],
            "references": [
                "https://en.wikipedia.org/wiki/Wavefront_.obj_file"
            ]
        },
        "Jpg": {
            "tags": [
                "file format",
                "raster graphics"
            ],
            "references": [
                "https://en.wikipedia.org/wiki/JPEG"
            ]
        },
        "Xml": {
            "tags": [
                "file format",
                "structured data"
            ],
            "references": [
                "https://en.wikipedia.org/wiki/XML"
            ]
        },
        "Html": {
            "tags": [
                "file format",
                "web"
            ],
            "references": [
                "https://en.wikipedia.org/wiki/HTML"
            ]
        },
        "Ogg": {
            "tags": [
                "file format",
                "audio"
            ],
            "references": [
                "https://en.wikipedia.org/wiki/Ogg"
            ]
        },
        "Json": {
            "tags": [
                "file format",
                "structured data"
            ],
            "references": [
                "https://en.wikipedia.org/wiki/JSON"
            ]
        },
        "Wav": {
            "tags": [
                "file format",
                "audio"
            ],
            "references": [
                "https://en.wikipedia.org/wiki/WAV"
            ]
        },
        "Gltf": {
            "tags": [
                "file format",
                "3d graphics"
            ],
            "references": [
                "https://en.wikipedia.org/wiki/GlTF"
            ]
        },
        "Artnet4J": {
            "tags": [
                "library",
                "opensource"
            ],
            "references": [
                "https://code.google.com/archive/p/artnet4j/",
                "https://github.com/cansik/artnet4j"
            ],
            "dependsOn": [
                "Java"
            ],
            "supports": [
                "ArtNet"
            ]
        },
        "JavaCv": {
            "tags": [
                "library"
            ],
            "dependsOn": [
                "Java",
                "OpenCv"
            ]
        },
        "JSerialComm": {
            "tags": [
                "library",
                "binding",
                "opensource"
            ],
            "references": [
                "https://github.com/Fazecast/jSerialComm"
            ],
            "dependsOn": [
                "java"
            ]
        },
        "Awt": {
            "tags": [
                "library",
                "ui"
            ],
            "references": [
                "https://en.wikipedia.org/wiki/Abstract_Window_Toolkit"
            ],
            "dependsOn": [
                "Java"
            ]
        },
        "BoofCV": {
            "tags": [
                "library"
            ],
            "references": [
                "https://boofcv.org/"
            ],
            "dependsOn": [
                "Java"
            ],
            "supports": [
                "Png",
                "Jpg"
            ]
        },
        "Antlr": {
            "tags": [
                "library",
                "parsing",
                "opensource"
            ],
            "references": [
                "https://en.wikipedia.org/wiki/ANTLR"
            ],
            "dependsOn": [
                "Java"
            ]
        },
        "Swing": {
            "tags": [
                "library",
                "ui"
            ],
            "references": [
                "https://en.wikipedia.org/wiki/Swing_(Java)"
            ],
            "dependsOn": [
                "Java"
            ]
        },
        "Jts": {
            "tags": [
                "library",
                "geometry",
                "gis",
                "opensource"
            ],
            "references": [
                "https://en.wikipedia.org/wiki/JTS_Topology_Suite",
                "https://github.com/locationtech/jts"
            ],
            "dependsOn": [
                "Java"
            ]
        },
        "JavaOsc": {
            "tags": [
                "library",
                "opensource"
            ],
            "references": [
                "https://github.com/hoijui/JavaOSC"
            ],
            "dependsOn": [
                "Java"
            ],
            "supports": [
                "Osc"
            ]
        },
        "Lwjgl": {
            "tags": [
                "library",
                "binding",
                "opensource"
            ],
            "references": [
                "https://en.wikipedia.org/wiki/LWJGL"
            ],
            "dependsOn": [
                "Java"
            ],
            "supports": [
                "Glfw",
                "Sdl"
            ]
        },
        "JavaxSound": {
            "tags": [
                "library"
            ],
            "dependsOn": [
                "Java"
            ],
            "supports": [
                "Wav"
            ]
        },
        "JavaxMidi": {
            "tags": [
                "library"
            ],
            "dependsOn": [
                "Java"
            ],
            "supports": [
                "Midi"
            ]
        },
        "Java": {
            "tags": [
                "language",
                "opensource"
            ]
        },
        "Jogl": {
            "tags": [
                "library",
                "binding",
                "opensource"
            ],
            "references": [
                "https://en.wikipedia.org/wiki/Java_OpenGL"
            ],
            "dependsOn": [
                "Java"
            ]
        },
        "OrxNoise": {
            "tags": [
                "library",
                "noise"
            ],
            "actions": {
                "generatePerlinNoise1D": {
                    "description": "Generate 1D Perlin noise",
                    "techniques": [
                        "PerlinNoise"
                    ]
                },
                "generatePerlinNoise3D": {
                    "description": "Generate 3D Perlin noise",
                    "techniques": [
                        "PerlinNoise"
                    ]
                },
                "generatePerlinNoise2D": {
                    "description": "Generate 2D Perlin noise",
                    "techniques": [
                        "PerlinNoise"
                    ]
                },
                "generateSimplexNoise1D": {
                    "description": "Generate 1D simplex noise",
                    "techniques": [
                        "SimplexNoise"
                    ]
                },
                "generateSimplexNoise3D": {
                    "description": "Generate 3D simplex noise",
                    "techniques": [
                        "SimplexNoise"
                    ]
                },
                "generateSimplexNoise4D": {
                    "description": "Generate 4D simplex noise",
                    "techniques": [
                        "SimplexNoise"
                    ]
                },
                "generateSimplexNoise2D": {
                    "description": "Generate 2D simplex noise",
                    "techniques": [
                        "SimplexNoise"
                    ]
                },
                "generatePerlinNoise4D": {
                    "description": "Generate 4D Perlin noise",
                    "techniques": [
                        "PerlinNoise"
                    ]
                },
                "generateFBM": {
                    "description": "Generate FBM noise",
                    "techniques": [
                        "FBMNoise"
                    ]
                }
            },
            "dependsOn": [
                "OPENRNDR"
            ]
        },
        "OrxFx": {
            "tags": [
                "library",
                "shaders"
            ],
            "actions": {
                "applyCannyEdgeDetector": {
                    "description": "Apply Canny edge detector",
                    "arguments": [
                        {
                            "name": "treshold0",
                            "type": "Number"
                        },
                        {
                            "name": "treshold1",
                            "type": "Number"
                        }
                    ],
                    "techniques": [
                        "CannyEdgeDetection"
                    ]
                },
                "applyGaussianBlur": {
                    "description": "Apply Gaussian blur",
                    "arguments": [
                        {
                            "name": "window",
                            "type": "Number"
                        },
                        {
                            "name": "sigma",
                            "type": "Number"
                        }
                    ],
                    "techniques": [
                        "GaussianBlur"
                    ]
                },
                "applyBloom": {
                    "description": "Apply bloom",
                    "arguments": [
                        {
                            "name": "window",
                            "type": "Number"
                        },
                        {
                            "name": "sigma",
                            "type": "Number"
                        }
                    ],
                    "techniques": [
                        "Bloom"
                    ]
                }
            },
            "dependsOn": [
                "OPENRNDR"
            ]
        },
        "OrxTextWriter": {
            "tags": [
                "library",
                "text"
            ],
            "dependsOn": [
                "OPENRNDR"
            ]
        },
        "OrxBoofCv": {
            "tags": [
                "library"
            ],
            "dependsOn": [
                "OPENRNDR",
                "BoofCV"
            ]
        },
        "OrxShapes": {
            "tags": [
                "library",
                "geometry"
            ],
            "actions": {
                "findDelaunayTriangulation": {
                    "description": "Find Delaunay triangulation",
                    "techniques": [
                        "DelaunayTriangulation"
                    ]
                },
                "fitHobbyCurve": {
                    "description": "Fit Hobby curve",
                    "techniques": [
                        "HobbyCurve"
                    ]
                }
            },
            "dependsOn": [
                "OPENRNDR"
            ]
        },
        "OpenrndrVideo": {
            "tags": [
                "library",
                "video"
            ],
            "dependsOn": [
                "OPENRNDR",
                "Ffmpeg"
            ],
            "supports": [
                "Mp4",
                "Mov"
            ]
        },
        "OrxMarchingSquares": {
            "tags": [
                "library",
                "geometry"
            ],
            "actions": {
                "extractIsoContour": {
                    "description": "Extract iso contour",
                    "techniques": [
                        "MarchingSquares"
                    ]
                }
            },
            "dependsOn": [
                "OPENRNDR"
            ]
        },
        "OrxMidi": {
            "tags": [
                "library"
            ],
            "dependsOn": [
                "OPENRNDR",
                "JavaxMidi"
            ],
            "supports": [
                "Midi"
            ]
        },
        "OPENRNDR": {
            "prototypes": [
                "_ImageIO",
                "_VideoIO",
                "_LibraryIO",
                "_Drawing"
            ],
            "tags": [
                "creative coding",
                "library",
                "opensource"
            ],
            "references": [
                "https://openrndr.org"
            ],
            "actions": {
                "loadImageArtifact": {
                    "description": "Load image artifact",
                    "arguments": [
                        {
                            "name": "name",
                            "type": "IArtifact"
                        }
                    ]
                },
                "saveImage": {
                    "description": "Save Image",
                    "arguments": [
                        {
                            "name": "name"
                        }
                    ],
                    "outputType": "FileArtifact"
                },
                "loadImage": {
                    "description": "Load Image",
                    "arguments": [
                        {
                            "name": "name"
                        }
                    ]
                },
                "createImage": {
                    "description": "Create an image",
                    "arguments": [
                        {
                            "name": "width",
                            "type": "Int"
                        },
                        {
                            "name": "height",
                            "type": "Int"
                        }
                    ]
                },
                "loadVideo": {
                    "description": "Load Video",
                    "arguments": [
                        {
                            "name": "name"
                        }
                    ],
                    "outputType": "VideoArtifact"
                },
                "saveVideo": {
                    "description": "Save Video",
                    "arguments": [
                        {
                            "name": "name"
                        }
                    ]
                },
                "importLibrary": {
                    "description": "Import library",
                    "arguments": [
                        {
                            "name": "libraryName"
                        }
                    ],
                    "outputType": "SourceCodeArtifact"
                },
                "clearBackground": {
                    "description": "Clear the background",
                    "arguments": [
                        {
                            "name": "red",
                            "type": "Number"
                        },
                        {
                            "name": "green",
                            "type": "Number"
                        },
                        {
                            "name": "blue",
                            "type": "Number"
                        }
                    ]
                },
                "drawEllipse": {
                    "description": "Draw an ellipse",
                    "arguments": [
                        {
                            "name": "x",
                            "type": "Number"
                        },
                        {
                            "name": "y",
                            "type": "Number"
                        },
                        {
                            "name": "xRadius",
                            "type": "Number"
                        },
                        {
                            "name": "yRadius",
                            "type": "Number"
                        }
                    ]
                },
                "drawCircle": {
                    "description": "Draw a circle",
                    "arguments": [
                        {
                            "name": "x",
                            "type": "Number"
                        },
                        {
                            "name": "y",
                            "type": "Number"
                        },
                        {
                            "name": "radius",
                            "type": "Number"
                        }
                    ]
                },
                "drawLine": {
                    "description": "Draw a line",
                    "arguments": [
                        {
                            "name": "x0",
                            "type": "Number"
                        },
                        {
                            "name": "y0",
                            "type": "Number"
                        },
                        {
                            "name": "x1",
                            "type": "Number"
                        },
                        {
                            "name": "y1",
                            "type": "Number"
                        }
                    ]
                },
                "drawCubicBezier": {
                    "description": "Draw a cubic bezier curve",
                    "arguments": [
                        {
                            "name": "x0",
                            "type": "Number"
                        },
                        {
                            "name": "y0",
                            "type": "Number"
                        },
                        {
                            "name": "x1",
                            "type": "Number"
                        },
                        {
                            "name": "y1",
                            "type": "Number"
                        },
                        {
                            "name": "x2",
                            "type": "Number"
                        },
                        {
                            "name": "y2",
                            "type": "Number"
                        },
                        {
                            "name": "x3",
                            "type": "Number"
                        },
                        {
                            "name": "y3",
                            "type": "Number"
                        }
                    ]
                },
                "drawQuadraticBezier": {
                    "description": "Draw a quadratic bezier curve",
                    "arguments": [
                        {
                            "name": "x0",
                            "type": "Number"
                        },
                        {
                            "name": "y0",
                            "type": "Number"
                        },
                        {
                            "name": "x1",
                            "type": "Number"
                        },
                        {
                            "name": "y1",
                            "type": "Number"
                        },
                        {
                            "name": "x2",
                            "type": "Number"
                        },
                        {
                            "name": "y2",
                            "type": "Number"
                        }
                    ]
                },
                "setStroke": {
                    "description": "Set the stroke color",
                    "arguments": [
                        {
                            "name": "red",
                            "type": "Number"
                        },
                        {
                            "name": "green",
                            "type": "Number"
                        },
                        {
                            "name": "blue",
                            "type": "Number"
                        },
                        {
                            "name": "alpha",
                            "type": "Number"
                        }
                    ]
                },
                "setFill": {
                    "description": "Set the fill color",
                    "arguments": [
                        {
                            "name": "red",
                            "type": "Number"
                        },
                        {
                            "name": "green",
                            "type": "Number"
                        },
                        {
                            "name": "blue",
                            "type": "Number"
                        },
                        {
                            "name": "alpha",
                            "type": "Number"
                        }
                    ]
                },
                "drawRectangle": {
                    "description": "Draw a rectangle",
                    "arguments": [
                        {
                            "name": "x",
                            "type": "Number"
                        },
                        {
                            "name": "y",
                            "type": "Number"
                        },
                        {
                            "name": "width",
                            "type": "Number"
                        },
                        {
                            "name": "height",
                            "type": "Number"
                        }
                    ]
                },
                "drawImage": {
                    "description": "Draw an image",
                    "arguments": [
                        {
                            "name": "x",
                            "type": "Number"
                        },
                        {
                            "name": "y",
                            "type": "Number"
                        },
                        {
                            "name": "width",
                            "type": "Number"
                        },
                        {
                            "name": "height",
                            "type": "Number"
                        }
                    ]
                },
                "setFont": {
                    "description": "Set the active font",
                    "arguments": [
                        {
                            "name": "font"
                        },
                        {
                            "name": "size",
                            "type": "Number"
                        }
                    ]
                },
                "drawText": {
                    "description": "Draw a text",
                    "arguments": [
                        {
                            "name": "x",
                            "type": "Number"
                        },
                        {
                            "name": "y",
                            "type": "Number"
                        },
                        {
                            "name": "text"
                        }
                    ]
                },
                "drawPoint": {
                    "description": "Draw a point",
                    "arguments": [
                        {
                            "name": "x",
                            "type": "Number"
                        },
                        {
                            "name": "y",
                            "type": "Number"
                        }
                    ]
                },
                "exportApplication": {
                    "description": "Export Application"
                }
            },
            "dependsOn": [
                "Kotlin",
                "Lwjgl"
            ],
            "supports": [
                "Png",
                "Svg",
                "Jpg"
            ]
        },
        "OrxSvg": {
            "tags": [
                "library"
            ],
            "dependsOn": [
                "OPENRNDR"
            ],
            "supports": [
                "Svg"
            ]
        },
        "OrxDnky": {
            "tags": [
                "library"
            ],
            "dependsOn": [
                "OPENRNDR"
            ],
            "supports": [
                "GLSL",
                "Gltf"
            ]
        },
        "OrxFft": {
            "tags": [
                "library"
            ],
            "actions": {
                "forwardFft": {
                    "description": "apply forward fft",
                    "techniques": [
                        "FFT"
                    ]
                }
            },
            "dependsOn": [
                "OPENRNDR"
            ]
        },
        "OrxOsc": {
            "tags": [
                "library"
            ],
            "dependsOn": [
                "OPENRNDR",
                "JavaOsc"
            ],
            "supports": [
                "Osc"
            ]
        },
        "OrxShadeStyles": {
            "tags": [
                "library",
                "shaders"
            ],
            "dependsOn": [
                "OPENRNDR"
            ],
            "supports": [
                "GLSL"
            ]
        },
        "Http": {
            "tags": [
                "protocol"
            ],
            "references": [
                "https://en.wikipedia.org/wiki/HTTP"
            ]
        },
        "ArtNet": {
            "tags": [
                "protocol"
            ],
            "references": [
                "https://en.wikipedia.org/wiki/Art-Net"
            ],
            "dependsOn": [
                "Udp"
            ],
            "supports": [
                "DMX"
            ]
        },
        "Https": {
            "tags": [
                "protocol"
            ],
            "references": [
                "https://en.wikipedia.org/wiki/HTTPS"
            ]
        },
        "WebSocket": {
            "tags": [
                "protocol"
            ],
            "references": [
                "https://en.wikipedia.org/wiki/WebSocket"
            ]
        },
        "Tcp": {
            "tags": [
                "protocol"
            ],
            "references": [
                "https://en.wikipedia.org/wiki/Transmission_Control_Protocol"
            ]
        },
        "Udp": {
            "tags": [
                "protocol"
            ],
            "references": [
                "https://en.wikipedia.org/wiki/User_Datagram_Protocol"
            ]
        },
        "OSC": {
            "tags": [
                "standard",
                "device interface"
            ],
            "references": [
                "https://en.wikipedia.org/wiki/Open_Sound_Control"
            ],
            "dependsOn": [
                "Udp"
            ]
        }
    }
}