{
    "tools": {
        "Illustrator": {
            "tags": [
                "application",
                "vector graphics"
            ],
            "references": [
                "https://en.wikipedia.org/wiki/Adobe_Illustrator"
            ]
        },
        "Vulkan": {
            "tags": [
                "library",
                "graphics api"
            ],
            "references": [
                "https://en.wikipedia.org/wiki/Vulkan"
            ]
        },
        "ImageMagick": {
            "tags": [
                "application",
                "raster graphics",
                "vector graphics",
                "command-line",
                "opensource"
            ],
            "references": [
                "https://en.wikipedia.org/wiki/ImageMagick",
                "https://imagemagick.org/"
            ]
        },
        "Mp4": {
            "tags": [
                "file format",
                "video"
            ],
            "references": [
                "https://en.wikipedia.org/wiki/MP4_file_format"
            ]
        },
        "Display": {
            "tags": [
                "media technology",
                "hardware"
            ]
        },
        "Mp3": {
            "tags": [
                "file format",
                "audio"
            ],
            "references": [
                "https://en.wikipedia.org/wiki/MP3"
            ]
        },
        "Hydra": {
            "tags": [
                "creative coding",
                "shaders",
                "opensource"
            ],
            "references": [
                "https://hydra.ojack.xyz/"
            ],
            "dependsOn": [
                "Javascript",
                "WebGL"
            ]
        },
        "Camera": {
            "tags": [
                "media technology",
                "sensor",
                "hardware"
            ],
            "actions": {
                "capture": {
                    "description": "Capture a frame"
                }
            }
        },
        "Antlr": {
            "tags": [
                "library",
                "parsing"
            ],
            "references": [
                "https://en.wikipedia.org/wiki/ANTLR"
            ],
            "dependsOn": [
                "Java"
            ]
        },
        "Photoshop": {
            "tags": [
                "application",
                "raster graphics"
            ]
        },
        "Xml": {
            "tags": [
                "file format",
                "structured data"
            ],
            "references": [
                "https://en.wikipedia.org/wiki/XML"
            ]
        },
        "Inkscape": {
            "tags": [
                "application",
                "opensource",
                "vector graphics"
            ],
            "references": [
                "https://en.wikipedia.org/wiki/Inkscape"
            ]
        },
        "D3JS": {
            "tags": [
                "library",
                "web",
                "opensource"
            ]
        },
        "Gif": {
            "tags": [
                "file format",
                "raster graphics"
            ],
            "references": [
                "https://en.wikipedia.org/wiki/GIF"
            ]
        },
        "Arduino": {
            "tags": [
                "hardware",
                "microcontroller",
                "application",
                "opensource"
            ],
            "references": [
                "https://en.wikipedia.org/wiki/Arduino",
                "https://www.arduino.cc/"
            ]
        },
        "Sox": {
            "tags": [
                "application",
                "audio",
                "command-line",
                "opensource"
            ],
            "references": [
                "https://en.wikipedia.org/wiki/SoX"
            ]
        },
        "Godot": {
            "tags": [
                "game development"
            ],
            "references": [
                "https://en.wikipedia.org/wiki/Godot_(game_engine)"
            ],
            "dependsOn": [
                "CSharp",
                "CPP"
            ]
        },
        "CircuitPython": {
            "tags": [
                "language",
                "microcontroller",
                "opensource"
            ]
        },
        "ThreeJS": {
            "tags": [
                "creative coding",
                "library",
                "web",
                "opensource"
            ],
            "dependsOn": [
                "Javascript",
                "WebGL",
                "WebGPU"
            ]
        },
        "Cinder": {
            "tags": [
                "creative coding",
                "library",
                "opensource"
            ],
            "references": [
                "https://en.wikipedia.org/wiki/Cinder_(programming_library)"
            ],
            "dependsOn": [
                "CPP"
            ]
        },
        "MediaPlayer": {
            "tags": [
                "media technology",
                "hardware"
            ],
            "actions": {
                "play": {
                    "description": "Play media"
                },
                "stop": {
                    "description": "Stop media"
                }
            }
        },
        "DepthSensor": {
            "tags": [
                "media technology",
                "sensor",
                "hardware"
            ],
            "actions": {
                "capture": {
                    "description": "Capture a frame"
                }
            }
        },
        "Picotron": {
            "tags": [
                "fantasy console"
            ],
            "references": [
                "https://en.wikipedia.org/wiki/Picotron",
                "https://www.lexaloffle.com/picotron.php"
            ],
            "dependsOn": [
                "Lua"
            ]
        },
        "Lua": {
            "tags": [
                "language"
            ],
            "references": [
                "https://en.wikipedia.org/wiki/Lua_(programming_language)"
            ]
        },
        "Python": {
            "tags": [
                "language",
                "opensource"
            ],
            "references": [
                "https://www.python.org/",
                "https://en.wikipedia.org/wiki/Python_(programming_language)"
            ]
        },
        "Ogg": {
            "tags": [
                "file format",
                "audio"
            ],
            "references": [
                "https://en.wikipedia.org/wiki/Ogg"
            ]
        },
        "Jogl": {
            "tags": [
                "library",
                "binding"
            ],
            "references": [
                "https://en.wikipedia.org/wiki/Java_OpenGL"
            ],
            "dependsOn": [
                "Java"
            ]
        },
        "Projector": {
            "tags": [
                "media technology",
                "hardware"
            ],
            "actions": {
                "display": {
                    "description": "Project on surface",
                    "arguments": [
                        {
                            "name": "artifact",
                            "type": "IArtifact"
                        }
                    ],
                    "outputType": "PrintedArtifact"
                }
            }
        },
        "Ruby": {
            "tags": [
                "language",
                "opensource"
            ]
        },
        "Gimp": {
            "tags": [
                "application",
                "opensource",
                "raster graphics"
            ]
        },
        "Kotlin": {
            "tags": [
                "language"
            ],
            "references": [
                "https://kotlinlang.org/"
            ],
            "dependsOn": [
                "Java",
                "Javascript"
            ]
        },
        "PenPlotter": {
            "tags": [
                "media technology",
                "hardware",
                "print"
            ],
            "actions": {
                "plot": {
                    "description": "Plot on paper",
                    "arguments": [
                        {
                            "name": "artifact",
                            "type": "IArtifact"
                        }
                    ],
                    "outputType": "PrintedArtifact"
                }
            }
        },
        "Ffmpeg": {
            "tags": [
                "application",
                "library",
                "video",
                "command-line",
                "opensource"
            ],
            "references": [
                "https://en.wikipedia.org/wiki/FFmpeg"
            ],
            "dependsOn": [
                "C"
            ]
        },
        "Blender": {
            "tags": [
                "application",
                "opensource",
                "3d graphics"
            ],
            "references": [
                "https://en.wikipedia.org/wiki/Blender_(software)"
            ],
            "dependsOn": [
                "C",
                "Python"
            ]
        },
        "OpenGL_ES": {
            "tags": [
                "library",
                "graphics api"
            ],
            "references": [
                "https://en.wikipedia.org/wiki/OpenGL_ES"
            ]
        },
        "OPENRNDR": {
            "prototypes": [
                "_ImageIO",
                "_VideoIO",
                "_LibraryIO",
                "_Drawing"
            ],
            "tags": [
                "creative coding",
                "library",
                "opensource"
            ],
            "references": [
                "https://openrndr.org"
            ],
            "actions": {
                "loadImageArtifact": {
                    "description": "Load image artifact",
                    "arguments": [
                        {
                            "name": "name",
                            "type": "IArtifact"
                        }
                    ]
                },
                "saveImage": {
                    "description": "Save Image",
                    "arguments": [
                        {
                            "name": "name"
                        }
                    ],
                    "outputType": "FileArtifact"
                },
                "loadImage": {
                    "description": "Load Image",
                    "arguments": [
                        {
                            "name": "name"
                        }
                    ]
                },
                "createImage": {
                    "description": "Create an image",
                    "arguments": [
                        {
                            "name": "width",
                            "type": "Int"
                        },
                        {
                            "name": "height",
                            "type": "Int"
                        }
                    ]
                },
                "loadVideo": {
                    "description": "Load Video",
                    "arguments": [
                        {
                            "name": "name"
                        }
                    ],
                    "outputType": "VideoArtifact"
                },
                "saveVideo": {
                    "description": "Save Video",
                    "arguments": [
                        {
                            "name": "name"
                        }
                    ]
                },
                "importLibrary": {
                    "description": "Import library",
                    "arguments": [
                        {
                            "name": "libraryName"
                        }
                    ],
                    "outputType": "SourceCodeArtifact"
                },
                "clearBackground": {
                    "description": "Clear the background",
                    "arguments": [
                        {
                            "name": "red",
                            "type": "Number"
                        },
                        {
                            "name": "green",
                            "type": "Number"
                        },
                        {
                            "name": "blue",
                            "type": "Number"
                        }
                    ]
                },
                "drawEllipse": {
                    "description": "Draw an ellipse",
                    "arguments": [
                        {
                            "name": "x",
                            "type": "Number"
                        },
                        {
                            "name": "y",
                            "type": "Number"
                        },
                        {
                            "name": "xRadius",
                            "type": "Number"
                        },
                        {
                            "name": "yRadius",
                            "type": "Number"
                        }
                    ]
                },
                "drawCircle": {
                    "description": "Draw a circle",
                    "arguments": [
                        {
                            "name": "x",
                            "type": "Number"
                        },
                        {
                            "name": "y",
                            "type": "Number"
                        },
                        {
                            "name": "radius",
                            "type": "Number"
                        }
                    ]
                },
                "drawLine": {
                    "description": "Draw a line",
                    "arguments": [
                        {
                            "name": "x0",
                            "type": "Number"
                        },
                        {
                            "name": "y0",
                            "type": "Number"
                        },
                        {
                            "name": "x1",
                            "type": "Number"
                        },
                        {
                            "name": "y1",
                            "type": "Number"
                        }
                    ]
                },
                "drawCubicBezier": {
                    "description": "Draw a cubic bezier curve",
                    "arguments": [
                        {
                            "name": "x0",
                            "type": "Number"
                        },
                        {
                            "name": "y0",
                            "type": "Number"
                        },
                        {
                            "name": "x1",
                            "type": "Number"
                        },
                        {
                            "name": "y1",
                            "type": "Number"
                        },
                        {
                            "name": "x2",
                            "type": "Number"
                        },
                        {
                            "name": "y2",
                            "type": "Number"
                        },
                        {
                            "name": "x3",
                            "type": "Number"
                        },
                        {
                            "name": "y3",
                            "type": "Number"
                        }
                    ]
                },
                "drawQuadraticBezier": {
                    "description": "Draw a quadratic bezier curve",
                    "arguments": [
                        {
                            "name": "x0",
                            "type": "Number"
                        },
                        {
                            "name": "y0",
                            "type": "Number"
                        },
                        {
                            "name": "x1",
                            "type": "Number"
                        },
                        {
                            "name": "y1",
                            "type": "Number"
                        },
                        {
                            "name": "x2",
                            "type": "Number"
                        },
                        {
                            "name": "y2",
                            "type": "Number"
                        }
                    ]
                },
                "setStroke": {
                    "description": "Set the stroke color",
                    "arguments": [
                        {
                            "name": "red",
                            "type": "Number"
                        },
                        {
                            "name": "green",
                            "type": "Number"
                        },
                        {
                            "name": "blue",
                            "type": "Number"
                        },
                        {
                            "name": "alpha",
                            "type": "Number"
                        }
                    ]
                },
                "setFill": {
                    "description": "Set the fill color",
                    "arguments": [
                        {
                            "name": "red",
                            "type": "Number"
                        },
                        {
                            "name": "green",
                            "type": "Number"
                        },
                        {
                            "name": "blue",
                            "type": "Number"
                        },
                        {
                            "name": "alpha",
                            "type": "Number"
                        }
                    ]
                },
                "drawRectangle": {
                    "description": "Draw a rectangle",
                    "arguments": [
                        {
                            "name": "x",
                            "type": "Number"
                        },
                        {
                            "name": "y",
                            "type": "Number"
                        },
                        {
                            "name": "width",
                            "type": "Number"
                        },
                        {
                            "name": "height",
                            "type": "Number"
                        }
                    ]
                },
                "drawImage": {
                    "description": "Draw an image",
                    "arguments": [
                        {
                            "name": "x",
                            "type": "Number"
                        },
                        {
                            "name": "y",
                            "type": "Number"
                        },
                        {
                            "name": "width",
                            "type": "Number"
                        },
                        {
                            "name": "height",
                            "type": "Number"
                        }
                    ]
                },
                "setFont": {
                    "description": "Set the active font",
                    "arguments": [
                        {
                            "name": "font"
                        },
                        {
                            "name": "size",
                            "type": "Number"
                        }
                    ]
                },
                "drawText": {
                    "description": "Draw a text",
                    "arguments": [
                        {
                            "name": "x",
                            "type": "Number"
                        },
                        {
                            "name": "y",
                            "type": "Number"
                        },
                        {
                            "name": "text"
                        }
                    ]
                },
                "drawPoint": {
                    "description": "Draw a point",
                    "arguments": [
                        {
                            "name": "x",
                            "type": "Number"
                        },
                        {
                            "name": "y",
                            "type": "Number"
                        }
                    ]
                },
                "exportApplication": {
                    "description": "Export Application"
                }
            },
            "libraries": {
                "OrxShadeStyles": {},
                "OpenrndrVideo": {},
                "OrxShapes": {},
                "OrxFx": {
                    "actions": {
                        "applyGaussianBlur": {
                            "description": "Apply Gaussian blur",
                            "arguments": [
                                {
                                    "name": "window",
                                    "type": "Number"
                                }
                            ],
                            "techniques": [
                                "GaussianBlur"
                            ]
                        }
                    }
                },
                "OrxNoise": {},
                "OrxTextWriter": {}
            },
            "dependsOn": [
                "Kotlin",
                "OpenGL",
                "WebGL",
                "Ffmpeg"
            ]
        },
        "MicroPython": {
            "tags": [
                "language",
                "microcontroller",
                "opensource"
            ],
            "references": [
                "https://en.wikipedia.org/wiki/MicroPython"
            ]
        },
        "Microphone": {
            "tags": [
                "media technology",
                "hardware"
            ],
            "actions": {
                "capture": {
                    "description": "Capture sound",
                    "outputType": "AudioArtifact"
                }
            }
        },
        "PureData": {
            "tags": [
                "application",
                "opensource",
                "node-based"
            ]
        },
        "Direct3D": {
            "tags": [
                "library",
                "graphics api"
            ],
            "references": [
                "https://en.wikipedia.org/wiki/Direct3D"
            ]
        },
        "Unity": {
            "tags": [
                "game development"
            ],
            "references": [
                "https://en.wikipedia.org/wiki/Unity_(game_engine)"
            ],
            "dependsOn": [
                "CSharp",
                "CPP"
            ]
        },
        "IntelliJ": {
            "tags": [
                "application",
                "ide"
            ],
            "references": [
                "https://en.wikipedia.org/wiki/IntelliJ_IDEA"
            ]
        },
        "P5Js": {
            "prototypes": [
                "_ImageIO",
                "_VideoIO",
                "_LibraryIO",
                "_Drawing"
            ],
            "tags": [
                "creative coding",
                "application",
                "library",
                "web",
                "opensource"
            ],
            "references": [
                "https://en.wikipedia.org/wiki/Processing#p5.js"
            ],
            "actions": {
                "loadImageArtifact": {
                    "description": "Load image artifact",
                    "arguments": [
                        {
                            "name": "name",
                            "type": "IArtifact"
                        }
                    ]
                },
                "saveImage": {
                    "description": "Save Image",
                    "arguments": [
                        {
                            "name": "name"
                        }
                    ],
                    "outputType": "FileArtifact"
                },
                "loadImage": {
                    "description": "Load Image",
                    "arguments": [
                        {
                            "name": "name"
                        }
                    ]
                },
                "createImage": {
                    "description": "Create an image",
                    "arguments": [
                        {
                            "name": "width",
                            "type": "Int"
                        },
                        {
                            "name": "height",
                            "type": "Int"
                        }
                    ]
                },
                "loadVideo": {
                    "description": "Load Video",
                    "arguments": [
                        {
                            "name": "name"
                        }
                    ],
                    "outputType": "VideoArtifact"
                },
                "saveVideo": {
                    "description": "Save Video",
                    "arguments": [
                        {
                            "name": "name"
                        }
                    ]
                },
                "importLibrary": {
                    "description": "Import library",
                    "arguments": [
                        {
                            "name": "libraryName"
                        }
                    ],
                    "outputType": "SourceCodeArtifact"
                },
                "clearBackground": {
                    "description": "Clear the background",
                    "arguments": [
                        {
                            "name": "red",
                            "type": "Number"
                        },
                        {
                            "name": "green",
                            "type": "Number"
                        },
                        {
                            "name": "blue",
                            "type": "Number"
                        }
                    ]
                },
                "drawEllipse": {
                    "description": "Draw an ellipse",
                    "arguments": [
                        {
                            "name": "x",
                            "type": "Number"
                        },
                        {
                            "name": "y",
                            "type": "Number"
                        },
                        {
                            "name": "xRadius",
                            "type": "Number"
                        },
                        {
                            "name": "yRadius",
                            "type": "Number"
                        }
                    ]
                },
                "drawCircle": {
                    "description": "Draw a circle",
                    "arguments": [
                        {
                            "name": "x",
                            "type": "Number"
                        },
                        {
                            "name": "y",
                            "type": "Number"
                        },
                        {
                            "name": "radius",
                            "type": "Number"
                        }
                    ]
                },
                "drawLine": {
                    "description": "Draw a line",
                    "arguments": [
                        {
                            "name": "x0",
                            "type": "Number"
                        },
                        {
                            "name": "y0",
                            "type": "Number"
                        },
                        {
                            "name": "x1",
                            "type": "Number"
                        },
                        {
                            "name": "y1",
                            "type": "Number"
                        }
                    ]
                },
                "drawCubicBezier": {
                    "description": "Draw a cubic bezier curve",
                    "arguments": [
                        {
                            "name": "x0",
                            "type": "Number"
                        },
                        {
                            "name": "y0",
                            "type": "Number"
                        },
                        {
                            "name": "x1",
                            "type": "Number"
                        },
                        {
                            "name": "y1",
                            "type": "Number"
                        },
                        {
                            "name": "x2",
                            "type": "Number"
                        },
                        {
                            "name": "y2",
                            "type": "Number"
                        },
                        {
                            "name": "x3",
                            "type": "Number"
                        },
                        {
                            "name": "y3",
                            "type": "Number"
                        }
                    ]
                },
                "drawQuadraticBezier": {
                    "description": "Draw a quadratic bezier curve",
                    "arguments": [
                        {
                            "name": "x0",
                            "type": "Number"
                        },
                        {
                            "name": "y0",
                            "type": "Number"
                        },
                        {
                            "name": "x1",
                            "type": "Number"
                        },
                        {
                            "name": "y1",
                            "type": "Number"
                        },
                        {
                            "name": "x2",
                            "type": "Number"
                        },
                        {
                            "name": "y2",
                            "type": "Number"
                        }
                    ]
                },
                "setStroke": {
                    "description": "Set the stroke color",
                    "arguments": [
                        {
                            "name": "red",
                            "type": "Number"
                        },
                        {
                            "name": "green",
                            "type": "Number"
                        },
                        {
                            "name": "blue",
                            "type": "Number"
                        },
                        {
                            "name": "alpha",
                            "type": "Number"
                        }
                    ]
                },
                "setFill": {
                    "description": "Set the fill color",
                    "arguments": [
                        {
                            "name": "red",
                            "type": "Number"
                        },
                        {
                            "name": "green",
                            "type": "Number"
                        },
                        {
                            "name": "blue",
                            "type": "Number"
                        },
                        {
                            "name": "alpha",
                            "type": "Number"
                        }
                    ]
                },
                "drawRectangle": {
                    "description": "Draw a rectangle",
                    "arguments": [
                        {
                            "name": "x",
                            "type": "Number"
                        },
                        {
                            "name": "y",
                            "type": "Number"
                        },
                        {
                            "name": "width",
                            "type": "Number"
                        },
                        {
                            "name": "height",
                            "type": "Number"
                        }
                    ]
                },
                "drawImage": {
                    "description": "Draw an image",
                    "arguments": [
                        {
                            "name": "x",
                            "type": "Number"
                        },
                        {
                            "name": "y",
                            "type": "Number"
                        },
                        {
                            "name": "width",
                            "type": "Number"
                        },
                        {
                            "name": "height",
                            "type": "Number"
                        }
                    ]
                },
                "setFont": {
                    "description": "Set the active font",
                    "arguments": [
                        {
                            "name": "font"
                        },
                        {
                            "name": "size",
                            "type": "Number"
                        }
                    ]
                },
                "drawText": {
                    "description": "Draw a text",
                    "arguments": [
                        {
                            "name": "x",
                            "type": "Number"
                        },
                        {
                            "name": "y",
                            "type": "Number"
                        },
                        {
                            "name": "text"
                        }
                    ]
                },
                "drawPoint": {
                    "description": "Draw a point",
                    "arguments": [
                        {
                            "name": "x",
                            "type": "Number"
                        },
                        {
                            "name": "y",
                            "type": "Number"
                        }
                    ]
                },
                "runSketch": {
                    "description": "Run sketch",
                    "outputType": "ProcessArtifact"
                },
                "publishSketch": {
                    "description": "Publish sketch",
                    "outputType": "SourceCodeArtifact"
                }
            },
            "dependsOn": [
                "Javascript"
            ]
        },
        "Opus": {
            "tags": [
                "file format",
                "audio"
            ],
            "references": [
                "https://en.wikipedia.org/wiki/Opus_(audio_format)"
            ]
        },
        "CPP": {
            "tags": [
                "language"
            ],
            "references": [
                "https://en.wikipedia.org/wiki/C%2B%2B"
            ]
        },
        "Nodebox": {
            "tags": [
                "application",
                "opensource",
                "node-based"
            ],
            "dependsOn": [
                "Python"
            ]
        },
        "TouchDesigner": {
            "tags": [
                "application",
                "node-based"
            ]
        },
        "Tic80": {
            "tags": [
                "fantasy console"
            ],
            "references": [
                "https://en.wikipedia.org/wiki/TIC-80"
            ],
            "dependsOn": [
                "Lua"
            ]
        },
        "DMX": {
            "tags": [
                "standard",
                "device interface"
            ],
            "references": [
                "https://en.wikipedia.org/wiki/DMX"
            ]
        },
        "SuperCollider": {
            "tags": [
                "application",
                "opensource",
                "audio"
            ]
        },
        "Collada": {
            "tags": [
                "file format",
                "3d graphics"
            ],
            "references": [
                "https://en.wikipedia.org/wiki/COLLADA"
            ]
        },
        "Lwjgl": {
            "tags": [
                "library",
                "binding"
            ],
            "references": [
                "https://en.wikipedia.org/wiki/LWJGL"
            ],
            "dependsOn": [
                "Java"
            ]
        },
        "Pico8": {
            "tags": [
                "fantasy console"
            ],
            "references": [
                "https://en.wikipedia.org/wiki/PICO-8"
            ],
            "dependsOn": [
                "Lua"
            ]
        },
        "OpenGL": {
            "tags": [
                "library",
                "graphics api"
            ],
            "references": [
                "https://en.wikipedia.org/wiki/OpenGL"
            ]
        },
        "HLSL": {
            "tags": [
                "language",
                "shaders"
            ],
            "references": [
                "https://en.wikipedia.org/wiki/High-Level_Shader_Language"
            ],
            "dependsOn": [
                "Direct3D"
            ]
        },
        "MaxMsp": {
            "tags": [
                "application",
                "node-based"
            ]
        },
        "Json": {
            "tags": [
                "file format",
                "structured data"
            ],
            "references": [
                "https://en.wikipedia.org/wiki/JSON"
            ]
        },
        "Angle": {
            "tags": [
                "library",
                "graphics api"
            ],
            "references": [
                "https://en.wikipedia.org/wiki/ANGLE_(software)"
            ]
        },
        "WebGPU": {
            "tags": [
                "library",
                "graphics api",
                "web"
            ],
            "references": [
                "https://en.wikipedia.org/wiki/WebGPU"
            ]
        },
        "Cinema4D": {
            "tags": [
                "application",
                "3d graphics"
            ],
            "references": [
                "https://en.wikipedia.org/wiki/Cinema_4D"
            ]
        },
        "ScikitLearn": {
            "tags": [
                "library",
                "data science",
                "machine learning"
            ],
            "references": [
                "https://en.wikipedia.org/wiki/Scikit-learn"
            ],
            "dependsOn": [
                "Python"
            ]
        },
        "Mov": {
            "tags": [
                "file format",
                "video"
            ],
            "references": [
                "https://en.wikipedia.org/wiki/QuickTime_File_Format"
            ]
        },
        "PyTorch": {
            "tags": [
                "library",
                "machine learning"
            ],
            "references": [
                "https://en.wikipedia.org/wiki/PyTorch"
            ],
            "dependsOn": [
                "Python",
                "CPP"
            ]
        },
        "Metal": {
            "tags": [
                "library",
                "graphics api"
            ],
            "references": [
                "https://en.wikipedia.org/wiki/Metal_(API)"
            ]
        },
        "OpenProcessing": {
            "tags": [
                "creative coding",
                "platform"
            ],
            "dependsOn": [
                "P5Js"
            ]
        },
        "MidiKeyboard": {
            "tags": [
                "media technology",
                "hardware"
            ],
            "dependsOn": [
                "Midi"
            ]
        },
        "Rust": {
            "tags": [
                "language",
                "opensource"
            ]
        },
        "C": {
            "tags": [
                "language"
            ]
        },
        "Pandas": {
            "tags": [
                "library",
                "data science"
            ],
            "references": [
                "https://en.wikipedia.org/wiki/Pandas_(software)"
            ],
            "dependsOn": [
                "Python"
            ]
        },
        "OpenFrameworks": {
            "tags": [
                "creative coding",
                "opensource"
            ],
            "references": [
                "https://en.wikipedia.org/wiki/OpenFrameworks"
            ],
            "dependsOn": [
                "CPP"
            ]
        },
        "Nannou": {
            "tags": [
                "creative coding",
                "library",
                "opensource"
            ],
            "references": [
                "https://nannou.cc/"
            ],
            "dependsOn": [
                "Rust"
            ]
        },
        "Obj": {
            "tags": [
                "file format",
                "3d graphics"
            ],
            "references": [
                "https://en.wikipedia.org/wiki/Wavefront_.obj_file"
            ]
        },
        "Processing": {
            "prototypes": [
                "_ImageIO",
                "_VideoIO",
                "_LibraryIO",
                "_Drawing"
            ],
            "tags": [
                "creative coding",
                "application",
                "library",
                "opensource"
            ],
            "actions": {
                "loadImageArtifact": {
                    "description": "Load image artifact",
                    "arguments": [
                        {
                            "name": "name",
                            "type": "IArtifact"
                        }
                    ]
                },
                "saveImage": {
                    "description": "Save Image",
                    "arguments": [
                        {
                            "name": "name"
                        }
                    ],
                    "outputType": "FileArtifact"
                },
                "loadImage": {
                    "description": "Load Image",
                    "arguments": [
                        {
                            "name": "name"
                        }
                    ]
                },
                "createImage": {
                    "description": "Create an image",
                    "arguments": [
                        {
                            "name": "width",
                            "type": "Int"
                        },
                        {
                            "name": "height",
                            "type": "Int"
                        }
                    ]
                },
                "loadVideo": {
                    "description": "Load Video",
                    "arguments": [
                        {
                            "name": "name"
                        }
                    ],
                    "outputType": "VideoArtifact"
                },
                "saveVideo": {
                    "description": "Save Video",
                    "arguments": [
                        {
                            "name": "name"
                        }
                    ]
                },
                "importLibrary": {
                    "description": "Import library",
                    "arguments": [
                        {
                            "name": "libraryName"
                        }
                    ],
                    "outputType": "SourceCodeArtifact"
                },
                "clearBackground": {
                    "description": "Clear the background",
                    "arguments": [
                        {
                            "name": "red",
                            "type": "Number"
                        },
                        {
                            "name": "green",
                            "type": "Number"
                        },
                        {
                            "name": "blue",
                            "type": "Number"
                        }
                    ]
                },
                "drawEllipse": {
                    "description": "Draw an ellipse",
                    "arguments": [
                        {
                            "name": "x",
                            "type": "Number"
                        },
                        {
                            "name": "y",
                            "type": "Number"
                        },
                        {
                            "name": "xRadius",
                            "type": "Number"
                        },
                        {
                            "name": "yRadius",
                            "type": "Number"
                        }
                    ]
                },
                "drawCircle": {
                    "description": "Draw a circle",
                    "arguments": [
                        {
                            "name": "x",
                            "type": "Number"
                        },
                        {
                            "name": "y",
                            "type": "Number"
                        },
                        {
                            "name": "radius",
                            "type": "Number"
                        }
                    ]
                },
                "drawLine": {
                    "description": "Draw a line",
                    "arguments": [
                        {
                            "name": "x0",
                            "type": "Number"
                        },
                        {
                            "name": "y0",
                            "type": "Number"
                        },
                        {
                            "name": "x1",
                            "type": "Number"
                        },
                        {
                            "name": "y1",
                            "type": "Number"
                        }
                    ]
                },
                "drawCubicBezier": {
                    "description": "Draw a cubic bezier curve",
                    "arguments": [
                        {
                            "name": "x0",
                            "type": "Number"
                        },
                        {
                            "name": "y0",
                            "type": "Number"
                        },
                        {
                            "name": "x1",
                            "type": "Number"
                        },
                        {
                            "name": "y1",
                            "type": "Number"
                        },
                        {
                            "name": "x2",
                            "type": "Number"
                        },
                        {
                            "name": "y2",
                            "type": "Number"
                        },
                        {
                            "name": "x3",
                            "type": "Number"
                        },
                        {
                            "name": "y3",
                            "type": "Number"
                        }
                    ]
                },
                "drawQuadraticBezier": {
                    "description": "Draw a quadratic bezier curve",
                    "arguments": [
                        {
                            "name": "x0",
                            "type": "Number"
                        },
                        {
                            "name": "y0",
                            "type": "Number"
                        },
                        {
                            "name": "x1",
                            "type": "Number"
                        },
                        {
                            "name": "y1",
                            "type": "Number"
                        },
                        {
                            "name": "x2",
                            "type": "Number"
                        },
                        {
                            "name": "y2",
                            "type": "Number"
                        }
                    ]
                },
                "setStroke": {
                    "description": "Set the stroke color",
                    "arguments": [
                        {
                            "name": "red",
                            "type": "Number"
                        },
                        {
                            "name": "green",
                            "type": "Number"
                        },
                        {
                            "name": "blue",
                            "type": "Number"
                        },
                        {
                            "name": "alpha",
                            "type": "Number"
                        }
                    ]
                },
                "setFill": {
                    "description": "Set the fill color",
                    "arguments": [
                        {
                            "name": "red",
                            "type": "Number"
                        },
                        {
                            "name": "green",
                            "type": "Number"
                        },
                        {
                            "name": "blue",
                            "type": "Number"
                        },
                        {
                            "name": "alpha",
                            "type": "Number"
                        }
                    ]
                },
                "drawRectangle": {
                    "description": "Draw a rectangle",
                    "arguments": [
                        {
                            "name": "x",
                            "type": "Number"
                        },
                        {
                            "name": "y",
                            "type": "Number"
                        },
                        {
                            "name": "width",
                            "type": "Number"
                        },
                        {
                            "name": "height",
                            "type": "Number"
                        }
                    ]
                },
                "drawImage": {
                    "description": "Draw an image",
                    "arguments": [
                        {
                            "name": "x",
                            "type": "Number"
                        },
                        {
                            "name": "y",
                            "type": "Number"
                        },
                        {
                            "name": "width",
                            "type": "Number"
                        },
                        {
                            "name": "height",
                            "type": "Number"
                        }
                    ]
                },
                "setFont": {
                    "description": "Set the active font",
                    "arguments": [
                        {
                            "name": "font"
                        },
                        {
                            "name": "size",
                            "type": "Number"
                        }
                    ]
                },
                "drawText": {
                    "description": "Draw a text",
                    "arguments": [
                        {
                            "name": "x",
                            "type": "Number"
                        },
                        {
                            "name": "y",
                            "type": "Number"
                        },
                        {
                            "name": "text"
                        }
                    ]
                },
                "drawPoint": {
                    "description": "Draw a point",
                    "arguments": [
                        {
                            "name": "x",
                            "type": "Number"
                        },
                        {
                            "name": "y",
                            "type": "Number"
                        }
                    ]
                },
                "runSketch": {
                    "description": "Run sketch"
                }
            },
            "dependsOn": [
                "Java"
            ]
        },
        "WebGL": {
            "tags": [
                "library",
                "graphics api",
                "web"
            ],
            "references": [
                "https://en.wikipedia.org/wiki/WebGL"
            ]
        },
        "Midi": {
            "tags": [
                "standard",
                "device interface"
            ],
            "references": [
                "https://en.wikipedia.org/wiki/MIDI"
            ]
        },
        "GLSL": {
            "tags": [
                "language",
                "shaders"
            ],
            "references": [
                "https://en.wikipedia.org/wiki/OpenGL_Shading_Language"
            ],
            "dependsOn": [
                "OpenGL"
            ]
        },
        "Printer": {
            "tags": [
                "media technology",
                "hardware",
                "print"
            ],
            "actions": {
                "print": {
                    "description": "Print on paper",
                    "outputType": "PrintedArtifact"
                }
            }
        },
        "Figma": {
            "tags": [
                "application",
                "saas",
                "vector graphics",
                "raster graphics"
            ]
        },
        "Gltf": {
            "tags": [
                "file format",
                "3d graphics"
            ],
            "references": [
                "https://en.wikipedia.org/wiki/GlTF"
            ]
        },
        "MidiController": {
            "tags": [
                "media technology",
                "hardware"
            ],
            "dependsOn": [
                "Midi"
            ]
        },
        "PaperJs": {
            "tags": [
                "web",
                "library",
                "opensource"
            ],
            "references": [
                "http://paperjs.org/"
            ],
            "dependsOn": [
                "Javascript"
            ]
        },
        "VSCode": {
            "tags": [
                "application",
                "ide",
                "opensource"
            ],
            "references": [
                "https://en.wikipedia.org/wiki/Visual_Studio_Code"
            ]
        },
        "ShaderToy": {
            "tags": [
                "software",
                "platform",
                "web",
                "shaders"
            ],
            "references": [
                "https://www.shadertoy.com/",
                "https://en.wikipedia.org/wiki/Shadertoy"
            ],
            "actions": {
                "runShader": {
                    "description": "Run Shader"
                },
                "publishShader": {
                    "description": " Publish shader",
                    "outputType": "SourceCodeArtifact"
                }
            },
            "dependsOn": [
                "Javascript",
                "WebGL",
                "GLSL"
            ]
        },
        "Svg": {
            "tags": [
                "file format",
                "vector graphics"
            ],
            "references": [
                "https://en.wikipedia.org/wiki/SVG"
            ]
        },
        "Png": {
            "tags": [
                "file format",
                "raster graphics"
            ],
            "references": [
                "https://en.wikipedia.org/wiki/PNG"
            ]
        },
        "Yaml": {
            "tags": [
                "file format",
                "structured data"
            ],
            "references": [
                "https://en.wikipedia.org/wiki/YAML"
            ]
        },
        "Javascript": {
            "tags": [
                "language",
                "web"
            ]
        },
        "Ktor": {
            "dependsOn": [
                "Kotlin"
            ]
        },
        "Esp32": {
            "tags": [
                "hardware",
                "microcontroller"
            ],
            "references": [
                "https://en.wikipedia.org/wiki/ESP32"
            ]
        },
        "CSharp": {
            "tags": [
                "language"
            ]
        },
        "Csv": {
            "tags": [
                "file format",
                "structured data"
            ],
            "references": [
                "https://en.wikipedia.org/wiki/Comma-separated_values"
            ]
        },
        "OSC": {
            "tags": [
                "standard",
                "device interface"
            ],
            "references": [
                "https://en.wikipedia.org/wiki/Open_Sound_Control"
            ]
        },
        "Jpg": {
            "tags": [
                "file format",
                "raster graphics"
            ],
            "references": [
                "https://en.wikipedia.org/wiki/JPEG"
            ]
        },
        "Audacity": {
            "tags": [
                "application",
                "audio"
            ]
        },
        "Java": {
            "tags": [
                "language",
                "opensource"
            ]
        }
    }
}